dictionary_analyser/__init__.py
dictionary_analyser/analyser.py
dsl_dict_analyser/__init__.py
dsl_dict_analyser/analyser.py
dsl_dict_analyser/models/__init__.py
dsl_dict_analyser/models/about.py
dsl_dict_analyser/models/card.py
dsl_dict_analyser/models/constants.py
dsl_dict_analyser/models/dictionary.py
dsl_dict_analyser-0.0.6.dist-info/METADATA
dsl_dict_analyser-0.0.6.dist-info/WHEEL
dsl_dict_analyser-0.0.6.dist-info/top_level.txt
dsl_dict_analyser-0.0.6.dist-info/RECORD
