Metadata-Version: 2.1
Name: dsl-dict-analyser
Version: 0.0.6
Summary: A Python package for analysing dsl dictionaries. Dsl dictionary is a dict type for lingvo app.
Home-page: https://github.com/felikspeegel/dsl_dict_analyser
Author: Feliks Peegel
Author-email: felikspeegel@outlook.com
Classifier: Programming Language :: Python :: 3
Classifier: License :: OSI Approved :: MIT License
Requires-Python: >=3.6
